[{
    "File":"3dskinlayers-fabric-1.4.5-mc1.18.2.jar",
    "Size":437768,
    "Hash":"9b52fa801357ca52ed4e4eb22daa9365b40f7f2d",
    "DestinationPath":"mods/3dskinlayers-fabric-1.4.5-mc1.18.2.jar"
  },{
    "File":"AdditionalAdditions-4.0.3.jar",
    "Size":4160056,
    "Hash":"52e484e9968a4f62c9d0e0dd1df321a74110e318",
    "DestinationPath":"mods/AdditionalAdditions-4.0.3.jar"
  },{
    "File":"Adorn-3.5.0+1.18.2-fabric.jar",
    "Size":4208573,
    "Hash":"54dc846236010b1e22bfdb6b7d06a669f6ccfb5a",
    "DestinationPath":"mods/Adorn-3.5.0+1.18.2-fabric.jar"
  },{
    "File":"advancementinfo-1.18.2-fabric0.47.10-1.3.1.jar",
    "Size":1442876,
    "Hash":"c817fbc6798d50ad45f586a66d5b54dc4fa3bf33",
    "DestinationPath":"mods/advancementinfo-1.18.2-fabric0.47.10-1.3.1.jar"
  },{
    "File":"AdvancementPlaques-1.18-fabric-1.4.4.jar",
    "Size":185858,
    "Hash":"6707edc42f5932d8a5006c8fb77879da197cba59",
    "DestinationPath":"mods/AdvancementPlaques-1.18-fabric-1.4.4.jar"
  },{
    "File":"allium-0.2.2+1.18.2.jar",
    "Size":46796,
    "Hash":"d0c9ea312ad65cb563da848dfe401446408d7c18",
    "DestinationPath":"mods/allium-0.2.2+1.18.2.jar"
  },{
    "File":"appleskin-fabric-mc1.18.2-2.4.0.jar",
    "Size":912787,
    "Hash":"07cc0f6d00b184bef9c4390682c098d5ca52e67d",
    "DestinationPath":"mods/appleskin-fabric-mc1.18.2-2.4.0.jar"
  },{
    "File":"appliedenergistics2-11.0.0.jar",
    "Size":4922522,
    "Hash":"71ac17ff1414782def879309a06abbe69142e7bc",
    "DestinationPath":"mods/appliedenergistics2-11.0.0.jar"
  },{
    "File":"architectury-4.4.68.jar",
    "Size":573673,
    "Hash":"25caa4222a307016cb45cf8b6d27c09b507e2196",
    "DestinationPath":"mods/architectury-4.4.68.jar"
  },{
    "File":"axolotl-item-fix-1.1.3.jar",
    "Size":43657,
    "Hash":"f60f9ea1e6afded2935ba5b1406aedcf429c20f8",
    "DestinationPath":"mods/axolotl-item-fix-1.1.3.jar"
  },{
    "File":"badpackets-fabric-0.1.2.jar",
    "Size":25470,
    "Hash":"098653c88addec413623a78c20e2f001e5647079",
    "DestinationPath":"mods/badpackets-fabric-0.1.2.jar"
  },{
    "File":"bclib-1.4.6.jar",
    "Size":949796,
    "Hash":"6fd5874f036daf09fa0da9347cb5384759a6788c",
    "DestinationPath":"mods/bclib-1.4.6.jar"
  },{
    "File":"better-end-1.1.0.jar",
    "Size":91263949,
    "Hash":"92fc74d36218e1cd363288251241535fff2fcfde",
    "DestinationPath":"mods/better-end-1.1.0.jar"
  },{
    "File":"BetterF3-1.2.5-Fabric-1.18.2.jar",
    "Size":1400327,
    "Hash":"457734b8099afbda9218c59aa6f197e2a2cc8d65",
    "DestinationPath":"mods/BetterF3-1.2.5-Fabric-1.18.2.jar"
  },{
    "File":"biomemakeover-FABRIC-1.18.2-1.4.23.jar",
    "Size":6291697,
    "Hash":"b6d690e796096923337c5042e728b969b4dd6c57",
    "DestinationPath":"mods/biomemakeover-FABRIC-1.18.2-1.4.23.jar"
  },{
    "File":"bitsandchisels-2.6.8.jar",
    "Size":303324,
    "Hash":"a632973972e44107d24be34c6ade9ad01519babc",
    "DestinationPath":"mods/bitsandchisels-2.6.8.jar"
  },{
    "File":"blast-1.9.1.jar",
    "Size":168073,
    "Hash":"4cfd2cc08aba261fa63c1c8774f13fb23d0eca95",
    "DestinationPath":"mods/blast-1.9.1.jar"
  },{
    "File":"c2me-fabric-mc1.18.2-0.2.0+alpha.7.0-all.jar",
    "Size":1290009,
    "Hash":"972a35c39823885b2853d6a6053b13de53a01272",
    "DestinationPath":"mods/c2me-fabric-mc1.18.2-0.2.0+alpha.7.0-all.jar"
  },{
    "File":"carpet-extra-1.18.2-1.4.72.jar",
    "Size":189001,
    "Hash":"220d81edfeff213fc811c0b86bb2cbe64187eb66",
    "DestinationPath":"mods/carpet-extra-1.18.2-1.4.72.jar"
  },{
    "File":"carpet-fixes-1.18.x-1.7.9.jar",
    "Size":589272,
    "Hash":"ab53b0a37f0f65b2b37b0ba8b7c7361298109a2d",
    "DestinationPath":"mods/carpet-fixes-1.18.x-1.7.9.jar"
  },{
    "File":"cc-restitched-1.100.6.jar",
    "Size":3310021,
    "Hash":"2fa8a582d7fef34fbf1ed4e2cc8cb25b9c35ccb5",
    "DestinationPath":"mods/cc-restitched-1.100.6.jar"
  },{
    "File":"chisel-1.4.5+1.18.x.jar",
    "Size":5845201,
    "Hash":"a4de5291a26ac7fb2e1d0bc3ef244dda371dfd8f",
    "DestinationPath":"mods/chisel-1.4.5+1.18.x.jar"
  },{
    "File":"ClearDespawn-fabric-1.18.2-1.1.7.jar",
    "Size":18184,
    "Hash":"2dafad51e4ee153a884fe7cd12b928a5b2339f42",
    "DestinationPath":"mods/ClearDespawn-fabric-1.18.2-1.1.7.jar"
  },{
    "File":"cloth-config-6.2.62-fabric.jar",
    "Size":1122859,
    "Hash":"bc0f07805823fdab5c7376d8d2b314c1b109d402",
    "DestinationPath":"mods/cloth-config-6.2.62-fabric.jar"
  },{
    "File":"crawl-0.10.6.jar",
    "Size":98132,
    "Hash":"efe4f2852b4f76c870771131e232701de6ca09e3",
    "DestinationPath":"mods/crawl-0.10.6.jar"
  },{
    "File":"create-mc1.18.2_v0.4.1+586.jar",
    "Size":13744483,
    "Hash":"d6e7f9074c74e12063025c5a0de72f5d2c6c7595",
    "DestinationPath":"mods/create-mc1.18.2_v0.4.1+586.jar"
  },{
    "File":"creeper-spores-1.8.0.jar",
    "Size":67146,
    "Hash":"4f2e99f2769ed3036704d4b246d4116b4faa9fec",
    "DestinationPath":"mods/creeper-spores-1.8.0.jar"
  },{
    "File":"Croptopia-1.18.2-FABRIC-2.0.3.jar",
    "Size":2462717,
    "Hash":"fd26292fc51bc1f726eeecbaf91630019a8cad2c",
    "DestinationPath":"mods/Croptopia-1.18.2-FABRIC-2.0.3.jar"
  },{
    "File":"crossstitch-0.1.4.jar",
    "Size":5038,
    "Hash":"9e53c001e4035a330d8f87438d5c31df849e7d43",
    "DestinationPath":"mods/crossstitch-0.1.4.jar"
  },{
    "File":"dawn-3.3.1.jar",
    "Size":1147761,
    "Hash":"bd15a7bff39ac57ca825557eadc388111cc559f1",
    "DestinationPath":"mods/dawn-3.3.1.jar"
  },{
    "File":"Decorative+Blocks-fabric-1.18.2-2.1.0.jar",
    "Size":460743,
    "Hash":"2574749d52b69cea643898ddf0dc977be174f13e",
    "DestinationPath":"mods/Decorative+Blocks-fabric-1.18.2-2.1.0.jar"
  },{
    "File":"effective-1.2.1.jar",
    "Size":1722910,
    "Hash":"c2574017b53faff1f1ac2a46ee7baca234e62400",
    "DestinationPath":"mods/effective-1.2.1.jar"
  },{
    "File":"ellemes-container-library-1.4.0-beta.1+1.18.2-fabric.jar",
    "Size":99934,
    "Hash":"c3776fb7b60f1ee33b8d1e3d969e15f9f3589d6f",
    "DestinationPath":"mods/ellemes-container-library-1.4.0-beta.1+1.18.2-fabric.jar"
  },{
    "File":"elytratrinket-fabric-3.0.0-1.18.1.jar",
    "Size":29731,
    "Hash":"70a2317527da7712416f17207ce4a21c272f7a3f",
    "DestinationPath":"mods/elytratrinket-fabric-3.0.0-1.18.1.jar"
  },{
    "File":"expanded-armor-enchanting-1.0.2.jar",
    "Size":10450,
    "Hash":"c24578e7745aafa94333784863ae13c309643420",
    "DestinationPath":"mods/expanded-armor-enchanting-1.0.2.jar"
  },{
    "File":"expanded-axe-enchanting-1.0.3.jar",
    "Size":10529,
    "Hash":"5ad5c8314e18fd2caf6fb3130842f22ab256b0bc",
    "DestinationPath":"mods/expanded-axe-enchanting-1.0.3.jar"
  },{
    "File":"expanded-trident-enchanting-1.0.3.jar",
    "Size":12142,
    "Hash":"2ef17b0522fc0c9c5662d593fa59ca54b6654f93",
    "DestinationPath":"mods/expanded-trident-enchanting-1.0.3.jar"
  },{
    "File":"expanded-weapon-enchanting-1.0.2.jar",
    "Size":10301,
    "Hash":"428d135b2cc374b790ea49041c5e2814c6ceb000",
    "DestinationPath":"mods/expanded-weapon-enchanting-1.0.2.jar"
  },{
    "File":"expandedstorage-7.4.0-beta.2+1.18.2-fabric.jar",
    "Size":413607,
    "Hash":"4d91d898bd9c34fd6f692e985a0b374e9be90e70",
    "DestinationPath":"mods/expandedstorage-7.4.0-beta.2+1.18.2-fabric.jar"
  },{
    "File":"Fabric-1.18-SmoothSwapping-0.4.4.jar",
    "Size":919823,
    "Hash":"1078b602073479277cb110c20c17b86db55741e6",
    "DestinationPath":"mods/Fabric-1.18-SmoothSwapping-0.4.4.jar"
  },{
    "File":"fabric-carpet-1.18.2-1.4.69+v220331.jar",
    "Size":1479637,
    "Hash":"674c6810bfee5f75d8ce71059dfda015b4729838",
    "DestinationPath":"mods/fabric-carpet-1.18.2-1.4.69+v220331.jar"
  },{
    "File":"fabric-language-kotlin-1.7.4+kotlin.1.6.21.jar",
    "Size":6079386,
    "Hash":"57581e800d250c31aed8bc17fa7c2af9786c26a3",
    "DestinationPath":"mods/fabric-language-kotlin-1.7.4+kotlin.1.6.21.jar"
  },{
    "File":"FabricProxy-Lite-1.1.6.jar",
    "Size":150162,
    "Hash":"a7911405ce8f3c2126acde7a1cd1cf0c603b3f61",
    "DestinationPath":"mods/FabricProxy-Lite-1.1.6.jar"
  },{
    "File":"ferritecore-4.2.1-fabric.jar",
    "Size":119110,
    "Hash":"d5d047374981d614c2a53422be751dc1491f9cd0",
    "DestinationPath":"mods/ferritecore-4.2.1-fabric.jar"
  },{
    "File":"friendsandfoes-fabric-mc1.18.2-1.4.0.jar",
    "Size":1087175,
    "Hash":"3ab29fd74433a8245d355ad63b8b1eba51db46cf",
    "DestinationPath":"mods/friendsandfoes-fabric-mc1.18.2-1.4.0.jar"
  },{
    "File":"geckolib-fabric-1.18-3.0.42.jar",
    "Size":3580353,
    "Hash":"87f604e223aae2e260b58e38d6defe3e078b8b6e",
    "DestinationPath":"mods/geckolib-fabric-1.18-3.0.42.jar"
  },{
    "File":"here-be-no-dragons-1.0.0.jar",
    "Size":6533,
    "Hash":"0564401b5be9b9e510dee00faa0979ea8a822ac0",
    "DestinationPath":"mods/here-be-no-dragons-1.0.0.jar"
  },{
    "File":"Highlighter-1.18-fabric-1.1.2.jar",
    "Size":25246,
    "Hash":"726a560553293ca5ca0ea5e2138730bb4252b4be",
    "DestinationPath":"mods/Highlighter-1.18-fabric-1.1.2.jar"
  },{
    "File":"Iceberg-1.18.2-fabric-1.0.38.jar",
    "Size":78177,
    "Hash":"a77c1d4af4f974ca331b330fdf6c6ddcc7c2ffdb",
    "DestinationPath":"mods/Iceberg-1.18.2-fabric-1.0.38.jar"
  },{
    "File":"illuminations-1.10.4.jar",
    "Size":1265759,
    "Hash":"076c8fb7929dad53b5c1a727ec34a80d980c6d1f",
    "DestinationPath":"mods/illuminations-1.10.4.jar"
  },{
    "File":"impaled-1.1.3.jar",
    "Size":266374,
    "Hash":"c72a1fb9b3f410d1c190853dee6c58864ed6f1c3",
    "DestinationPath":"mods/impaled-1.1.3.jar"
  },{
    "File":"indium-1.0.3+mc1.18.2.jar",
    "Size":118295,
    "Hash":"a20793e65789fb9ef248d07dfd2fcd79e8afb53d",
    "DestinationPath":"mods/indium-1.0.3+mc1.18.2.jar"
  },{
    "File":"inmis-2.6.0-1.18.2.jar",
    "Size":152470,
    "Hash":"2c043c9c23d21c7d900637f88bab9d2075eaa124",
    "DestinationPath":"mods/inmis-2.6.0-1.18.2.jar"
  },{
    "File":"InventoryProfilesNext-fabric-1.18.2-1.5.0.jar",
    "Size":1537671,
    "Hash":"73c1c4077f30c7ac2f7cd9fda2678a80a41ec32e",
    "DestinationPath":"mods/InventoryProfilesNext-fabric-1.18.2-1.5.0.jar"
  },{
    "File":"InvView-1.4.8-1.18+.jar",
    "Size":147328,
    "Hash":"f225da7ae6b3327e36a017386d9d975c472a7303",
    "DestinationPath":"mods/InvView-1.4.8-1.18+.jar"
  },{
    "File":"kentucky-fried-axolotls-1.0.1-1.18.2.jar",
    "Size":15867,
    "Hash":"d78505c9d753e91653b327d8b7566136b77195d4",
    "DestinationPath":"mods/kentucky-fried-axolotls-1.0.1-1.18.2.jar"
  },{
    "File":"krypton-0.1.9.jar",
    "Size":132286,
    "Hash":"466a8a26949497a3b11886a788e6e156a8b03d24",
    "DestinationPath":"mods/krypton-0.1.9.jar"
  },{
    "File":"lambdabettergrass-1.2.3+1.18.jar",
    "Size":1151411,
    "Hash":"f5bdcf5dde183ca6c5b8ee28ab6193c1a9ef390d",
    "DestinationPath":"mods/lambdabettergrass-1.2.3+1.18.jar"
  },{
    "File":"lambdynamiclights-2.1.0+1.17.jar",
    "Size":592990,
    "Hash":"812fdc41518b786f05d72de4017c16c88a3e2ea6",
    "DestinationPath":"mods/lambdynamiclights-2.1.0+1.17.jar"
  },{
    "File":"lazydfu-0.1.2.jar",
    "Size":15517,
    "Hash":"2efec5781f1271bdcdae462eee402ccb97bff6fe",
    "DestinationPath":"mods/lazydfu-0.1.2.jar"
  },{
    "File":"ledger-1.2.4.jar",
    "Size":16732397,
    "Hash":"55845e0ab71515e27f4c7c77524a094b6189c10e",
    "DestinationPath":"mods/ledger-1.2.4.jar"
  },{
    "File":"lithium-fabric-mc1.18.2-0.7.10.jar",
    "Size":466196,
    "Hash":"d5c19c3d4edb4228652adcc8abb94f9bd80a634c",
    "DestinationPath":"mods/lithium-fabric-mc1.18.2-0.7.10.jar"
  },{
    "File":"mavm-fabric-1.18.1-1.0.7a.jar",
    "Size":50773,
    "Hash":"904c69a69c46695c75eee1e009310274d97ce48a",
    "DestinationPath":"mods/mavm-fabric-1.18.1-1.0.7a.jar"
  },{
    "File":"modmenu-3.2.2.jar",
    "Size":299929,
    "Hash":"d581615296b1dfb72477c984a43cc6891f75eb73",
    "DestinationPath":"mods/modmenu-3.2.2.jar"
  },{
    "File":"more-geodes-1.4.2.jar",
    "Size":66693,
    "Hash":"685d9409db69a1656640d72faa8abc2e1dc6246f",
    "DestinationPath":"mods/more-geodes-1.4.2.jar"
  },{
    "File":"more-totems-mod-2.10.0.jar",
    "Size":50738,
    "Hash":"1d2b73f73c865492f28f1f5ccbddaa6a3c0c6ad9",
    "DestinationPath":"mods/more-totems-mod-2.10.0.jar"
  },{
    "File":"morevillagers-FABRIC-1.18.2-3.2.0.jar",
    "Size":1243490,
    "Hash":"cb535a7d0949495ebfcb14df91dd94886e56b848",
    "DestinationPath":"mods/morevillagers-FABRIC-1.18.2-3.2.0.jar"
  },{
    "File":"no-telemetry-1.3.0.jar",
    "Size":84523,
    "Hash":"0aa4244d3f97006cb4bacbdefbd9ea41e17f1400",
    "DestinationPath":"mods/no-telemetry-1.3.0.jar"
  },{
    "File":"Oh_The_Biomes_You'll_Go-fabric-1.18.2-1.4-RC-21.jar",
    "Size":13318779,
    "Hash":"3d8022940f36a06a9de6176a457a0171b16070bb",
    "DestinationPath":"mods/Oh_The_Biomes_You'll_Go-fabric-1.18.2-1.4-RC-21.jar"
  },{
    "File":"ok_zoomer-5.0.0-beta.7+1.18.2.jar",
    "Size":264173,
    "Hash":"3607c558bfe465c4bdde3d1599a2748e315b41f8",
    "DestinationPath":"mods/ok_zoomer-5.0.0-beta.7+1.18.2.jar"
  },{
    "File":"PerfectAccuracy-1.2.jar",
    "Size":147001,
    "Hash":"53344dc5645a75f5954fbfd2908112c3c5124bf5",
    "DestinationPath":"mods/PerfectAccuracy-1.2.jar"
  },{
    "File":"Peripheralium-0.1.1.jar",
    "Size":198408,
    "Hash":"f87a16e4ae6b82df70cce3e38f54fa434507a474",
    "DestinationPath":"mods/Peripheralium-0.1.1.jar"
  },{
    "File":"peripheralworks-0.1.2.jar",
    "Size":97682,
    "Hash":"1fbe6be8c9b585211657f75761ef8a82ae44ed36",
    "DestinationPath":"mods/peripheralworks-0.1.2.jar"
  },{
    "File":"phosphor-fabric-mc1.18.x-0.8.1.jar",
    "Size":90017,
    "Hash":"9b826d21b9cd999853a57c76b0c47ee4d9161dc9",
    "DestinationPath":"mods/phosphor-fabric-mc1.18.x-0.8.1.jar"
  },{
    "File":"pickyourpoison-1.0.7.jar",
    "Size":505228,
    "Hash":"14ae90cd609de49f6f0d3e2aadd73d6736bb56d1",
    "DestinationPath":"mods/pickyourpoison-1.0.7.jar"
  },{
    "File":"plushie-mod-1.2-1.18.1.jar",
    "Size":186432,
    "Hash":"8cb1420651dbc2f4b81015c9945bfdc99624957c",
    "DestinationPath":"mods/plushie-mod-1.2-1.18.1.jar"
  },{
    "File":"polymer-all-0.2.0-pre.6+1.18.2.jar",
    "Size":500122,
    "Hash":"1c988f93e01d7df8f3d81b6fbe77133596959f8d",
    "DestinationPath":"mods/polymer-all-0.2.0-pre.6+1.18.2.jar"
  },{
    "File":"polymorph-fabric-0.0.21-1.18.2.jar",
    "Size":330319,
    "Hash":"3b8443435450295ace708b2062aa1dc9c3847956",
    "DestinationPath":"mods/polymorph-fabric-0.0.21-1.18.2.jar"
  },{
    "File":"post-materia-1.0.0-1.18.2.jar",
    "Size":344723,
    "Hash":"cf2b46b8103fd3e91b540ee9b333aec484265006",
    "DestinationPath":"mods/post-materia-1.0.0-1.18.2.jar"
  },{
    "File":"probablychests-0.4.3.jar",
    "Size":627686,
    "Hash":"d71d05e0112d3962bf091c3cd55f40892904d6ae",
    "DestinationPath":"mods/probablychests-0.4.3.jar"
  },{
    "File":"PuzzlesLib-v3.3.5-1.18.2-Fabric.jar",
    "Size":403866,
    "Hash":"9af22a06555f52ec9246f61d61529f2c23fa7ffb",
    "DestinationPath":"mods/PuzzlesLib-v3.3.5-1.18.2-Fabric.jar"
  },{
    "File":"qsl-1.1.0-beta.13_qfapi-1.0.0-beta.16_fapi-0.53.4_mc-1.18.2.jar",
    "Size":1037687,
    "Hash":"6138f7108ba35be44515d275ace27340a061a51a",
    "DestinationPath":"mods/qsl-1.1.0-beta.13_qfapi-1.0.0-beta.16_fapi-0.53.4_mc-1.18.2.jar"
  },{
    "File":"qsl-1.1.0-beta.8_qfapi-1.0.0-beta.14_fapi-0.51.1_mc-1.18.2.jar.old",
    "Size":1006133,
    "Hash":"2f61dd13abae944fbdc8d506c72f1fa08576665b",
    "DestinationPath":"mods/qsl-1.1.0-beta.8_qfapi-1.0.0-beta.14_fapi-0.51.1_mc-1.18.2.jar.old"
  },{
    "File":"ratsmischief-1.3.7.jar",
    "Size":292508,
    "Hash":"0395feeb1dec01d46dde9b91f4953b1ead809aad",
    "DestinationPath":"mods/ratsmischief-1.3.7.jar"
  },{
    "File":"rer-2.5.0.jar.old",
    "Size":81566,
    "Hash":"d645beadf4b46b1c0b4921b24adf81887b6566d3",
    "DestinationPath":"mods/rer-2.5.0.jar.old"
  },{
    "File":"respawnablepets-1.18-4.jar",
    "Size":200424,
    "Hash":"8a2a2fba12138b08f19037fc2c026eac30315ae0",
    "DestinationPath":"mods/respawnablepets-1.18-4.jar"
  },{
    "File":"RoughlyEnoughItems-8.2.470.jar",
    "Size":1778445,
    "Hash":"6635f6351de0af0f4c12f1f5049ded9abd565b92",
    "DestinationPath":"mods/RoughlyEnoughItems-8.2.470.jar"
  },{
    "File":"RoughlyEnoughProfessions-fabric-1.18.2-1.0.1.jar.old",
    "Size":21210,
    "Hash":"f870f494ed856c0b0b0151dcd8a0c4edf1b9cf0a",
    "DestinationPath":"mods/RoughlyEnoughProfessions-fabric-1.18.2-1.0.1.jar.old"
  },{
    "File":"satin-1.7.2.jar",
    "Size":100239,
    "Hash":"97e2c04346a6e39d8525c131f85872cbb6cf8255",
    "DestinationPath":"mods/satin-1.7.2.jar"
  },{
    "File":"Server-Translations-1.4.12+1.18.2.jar",
    "Size":96517,
    "Hash":"b60eb11cf299e680c2867b246033ed3c0ac1785b",
    "DestinationPath":"mods/Server-Translations-1.4.12+1.18.2.jar"
  },{
    "File":"sodium-fabric-mc1.18.2-0.4.1+build.15.jar",
    "Size":1318645,
    "Hash":"f839863a6be7014b8d80058ea1f361521148d049",
    "DestinationPath":"mods/sodium-fabric-mc1.18.2-0.4.1+build.15.jar"
  },{
    "File":"soundphysics-fabric-1.18.2-1.0.6.jar",
    "Size":101638,
    "Hash":"414615a585c0d26bbf25f66a6608f06606fda4a5",
    "DestinationPath":"mods/soundphysics-fabric-1.18.2-1.0.6.jar"
  },{
    "File":"spark-1.9.1-fabric.jar",
    "Size":3244903,
    "Hash":"74626c3b0083d43caa2904162ba0c7880661af75",
    "DestinationPath":"mods/spark-1.9.1-fabric.jar"
  },{
    "File":"stendhal-1.3.1-1.18.jar",
    "Size":469915,
    "Hash":"a6de2a9487d13dbc48745be46e3b48279679c087",
    "DestinationPath":"mods/stendhal-1.3.1-1.18.jar"
  },{
    "File":"TerraBlender-fabric-1.18.2-1.1.0.101.jar",
    "Size":306885,
    "Hash":"cda21674294abea7bcac6f60b7b83e382c9b2de6",
    "DestinationPath":"mods/TerraBlender-fabric-1.18.2-1.1.0.101.jar"
  },{
    "File":"trade-cycling-fabric-1.18.2-1.0.2.jar",
    "Size":285034,
    "Hash":"75211e8fa6abe8f23d2e98d3c3b3deae567eecd0",
    "DestinationPath":"mods/trade-cycling-fabric-1.18.2-1.0.2.jar"
  },{
    "File":"TradingPost-v3.2.0-1.18.2-Fabric.jar",
    "Size":406824,
    "Hash":"93255969543c7da4e505821a31acfe236f8a7f00",
    "DestinationPath":"mods/TradingPost-v3.2.0-1.18.2-Fabric.jar"
  },{
    "File":"trinketofundying-fabric-2.0.1-1.18.jar",
    "Size":28814,
    "Hash":"70f8a18fb914e170342b0657ecc18847f2800dc2",
    "DestinationPath":"mods/trinketofundying-fabric-2.0.1-1.18.jar"
  },{
    "File":"trinkets-3.3.1.jar",
    "Size":230557,
    "Hash":"1f6784a63d0c4cfe6caacf7b7a93ddd9f0b4e491",
    "DestinationPath":"mods/trinkets-3.3.1.jar"
  },{
    "File":"turtlematic-0.4.3.jar",
    "Size":464005,
    "Hash":"098c722166656a0ffa277baf0285638907ef4779",
    "DestinationPath":"mods/turtlematic-0.4.3.jar"
  },{
    "File":"universal_ores-1.2.1.jar",
    "Size":193830,
    "Hash":"52f264d2c841c8c7a38a591365aaf2d55aba5b78",
    "DestinationPath":"mods/universal_ores-1.2.1.jar"
  },{
    "File":"vanish-1.18-1.4.0.jar",
    "Size":61290,
    "Hash":"58a787a19f31dcb5776b7818b17f228f418c8730",
    "DestinationPath":"mods/vanish-1.18-1.4.0.jar"
  },{
    "File":"VanitySlots-1.1.2.jar",
    "Size":55099,
    "Hash":"266ed489705f45c5080865bf60f6d330548a887e",
    "DestinationPath":"mods/VanitySlots-1.1.2.jar"
  },{
    "File":"veinmining-fabric-0.0.12-1.18.2.jar",
    "Size":64033,
    "Hash":"f2d087adaae6b5964cba3b0d62b3d522bf7b2fb8",
    "DestinationPath":"mods/veinmining-fabric-0.0.12-1.18.2.jar"
  },{
    "File":"villager-hats-1.4.0.jar",
    "Size":32182,
    "Hash":"42b4e61ffee12656fc6fef82cb5dffb9594f9393",
    "DestinationPath":"mods/villager-hats-1.4.0.jar"
  },{
    "File":"voicechat-fabric-1.18.2-2.2.32.jar",
    "Size":5563551,
    "Hash":"61aef2708186b6b9f8860aa2e6d1d0cbcec23f4b",
    "DestinationPath":"mods/voicechat-fabric-1.18.2-2.2.32.jar"
  },{
    "File":"worldedit-mod-7.2.10.jar",
    "Size":5500682,
    "Hash":"40fc7f7a734ccbd53365bc91c1a17fafcec1965d",
    "DestinationPath":"mods/worldedit-mod-7.2.10.jar"
  },{
    "File":"wraith-waystones-2.5.3.jar",
    "Size":341350,
    "Hash":"9a20e854631aeaa117067f8687c79aae7ffb70ff",
    "DestinationPath":"mods/wraith-waystones-2.5.3.jar"
  },{
    "File":"wthit-fabric-4.10.3.jar",
    "Size":336416,
    "Hash":"014f61ffa930eaf41dd48156e97dde63abe08327",
    "DestinationPath":"mods/wthit-fabric-4.10.3.jar"
  },{
    "File":"YungsApi-1.18.2-Fabric-2.0.8.jar",
    "Size":153151,
    "Hash":"4e96599a16b1eba26e2e712d5f282780dca58876",
    "DestinationPath":"mods/YungsApi-1.18.2-Fabric-2.0.8.jar"
  },{
    "File":"YungsBetterDungeons-1.18.2-Fabric-2.1.0.jar",
    "Size":1043010,
    "Hash":"60a2dcbf64e70a2f7b6e65d0ed2ce57bda5dbcee",
    "DestinationPath":"mods/YungsBetterDungeons-1.18.2-Fabric-2.1.0.jar"
  },{
    "File":"YungsBetterMineshafts-1.18.2-Fabric-2.1.3.jar",
    "Size":275631,
    "Hash":"c07de72403a39178ec49ba4a29b2d6b4a8a0aa38",
    "DestinationPath":"mods/YungsBetterMineshafts-1.18.2-Fabric-2.1.3.jar"
  },{
    "File":"YungsBetterStrongholds-1.18.2-Fabric-2.1.1.jar",
    "Size":607278,
    "Hash":"a52d3632a5e9a21d66ac6f8b8129b5e4f761a02d",
    "DestinationPath":"mods/YungsBetterStrongholds-1.18.2-Fabric-2.1.1.jar"
  },{
    "File":"YungsBridges-1.18.2-Fabric-2.1.0.jar.old",
    "Size":1068025,
    "Hash":"a1363bac63443bc795db9b50c53cb8f0798c0993",
    "DestinationPath":"mods/YungsBridges-1.18.2-Fabric-2.1.0.jar.old"
  },{
    "File":"YungsExtras-1.18.2-Fabric-2.1.0.jar",
    "Size":875230,
    "Hash":"ddbb5531fa49d3081a3be8342bb6c707c517c1e9",
    "DestinationPath":"mods/YungsExtras-1.18.2-Fabric-2.1.0.jar"
  },{
    "File":"additional-additions-config.json",
    "Size":889,
    "Hash":"b6f2652c1adbea3e52ac898c609218dd09fda1f3",
    "DestinationPath":"config/additional-additions-config.json"
  },{
    "File":"Adorn.json5",
    "Size":968,
    "Hash":"106d96862f82130fa897abe2da14719dbb6bd589",
    "DestinationPath":"config/Adorn.json5"
  },{
    "File":"advancementinfo.json5",
    "Size":146,
    "Hash":"1bbc4d83d98beefbc7ffb1094e751f45fe483819",
    "DestinationPath":"config/advancementinfo.json5"
  },{
    "File":"advancementplaques.json5",
    "Size":2066,
    "Hash":"2cb442fe09a6be07a3f6ca6512a28ebf0ce69184",
    "DestinationPath":"config/advancementplaques.json5"
  },{
    "File":"appleskin.json5",
    "Size":1327,
    "Hash":"4994b8afdf50b6412aa302a70c31a9f04bfb73fa",
    "DestinationPath":"config/appleskin.json5"
  },{
    "File":"client.json",
    "Size":508,
    "Hash":"bca5caa764289496e7d755689a13a336aee5f091",
    "DestinationPath":"config/appliedenergistics2/client.json"
  },{
    "File":"common.json",
    "Size":3647,
    "Hash":"940d4d45574b4d17e8b39bc0405f3a9b365729d2",
    "DestinationPath":"config/appliedenergistics2/common.json"
  },{
    "File":"biomes.json",
    "Size":5418,
    "Hash":"68b372a3508195ae166f25bc2f07f720d72ffa69",
    "DestinationPath":"config/bclib/biomes.json"
  },{
    "File":"client.json",
    "Size":465,
    "Hash":"33d2f62fc3c0bdae622730978c670a3ef0422e36",
    "DestinationPath":"config/bclib/client.json"
  },{
    "File":"generator.json",
    "Size":740,
    "Hash":"5b1e2be875b61adde39370c9351979e34242f7b4",
    "DestinationPath":"config/bclib/generator.json"
  },{
    "File":"main.json",
    "Size":111,
    "Hash":"87e552458ee1df4dcc2467a6bef5934846e7e503",
    "DestinationPath":"config/bclib/main.json"
  },{
    "File":"recipes.json",
    "Size":476,
    "Hash":"204b02af80946f14dd79b29d3442a38e83201d93",
    "DestinationPath":"config/bclib/recipes.json"
  },{
    "File":"server.json",
    "Size":320,
    "Hash":"2fb85f1df2754e7b71e66085182522cdffbe297a",
    "DestinationPath":"config/bclib/server.json"
  },{
    "File":"betterdungeons-fabric-1_18.toml",
    "Size":564,
    "Hash":"142a84e0d2140a0cf39dff2ca82c07efb1e2c625",
    "DestinationPath":"config/betterdungeons-fabric-1_18.toml"
  },{
    "File":"biomes.json",
    "Size":1763,
    "Hash":"f212cd138703d1e1f2f1d185ef00dd47cf12e5bb",
    "DestinationPath":"config/betterend/biomes.json"
  },{
    "File":"blocks.json",
    "Size":21498,
    "Hash":"0f761b5fb9f1d56b151e6575feca026c25d2a7a3",
    "DestinationPath":"config/betterend/blocks.json"
  },{
    "File":"client.json",
    "Size":167,
    "Hash":"6bcdba2ad4b3d2d6d7d6d7e782f6a133927df7d0",
    "DestinationPath":"config/betterend/client.json"
  },{
    "File":"enchantments.json",
    "Size":38,
    "Hash":"1a1874a232f8efabec80a4693ef2027a9f5e3d11",
    "DestinationPath":"config/betterend/enchantments.json"
  },{
    "File":"entities.json",
    "Size":225,
    "Hash":"49f24acceb23fb5cf8e8dbce8f8d9f3318eeaceb",
    "DestinationPath":"config/betterend/entities.json"
  },{
    "File":"generator.json",
    "Size":1825,
    "Hash":"9a7ead7c74e51bef4f817b2350929c160c016d44",
    "DestinationPath":"config/betterend/generator.json"
  },{
    "File":"items.json",
    "Size":5940,
    "Hash":"7d3842d09257e1448881f54d0bd2ad9cce7d9f4b",
    "DestinationPath":"config/betterend/items.json"
  },{
    "File":"portals.json",
    "Size":190,
    "Hash":"155613aade66441f1485e53ef459e1bba158b797",
    "DestinationPath":"config/betterend/portals.json"
  },{
    "File":"recipes.json",
    "Size":31592,
    "Hash":"ac26dae7e6b10ca8693cfa132a594d6e68298098",
    "DestinationPath":"config/betterend/recipes.json"
  },{
    "File":"betterf3.json",
    "Size":1373,
    "Hash":"b1988167b8adce9c88b43b519cd623f6475a441d",
    "DestinationPath":"config/betterf3.json"
  },{
    "File":"bettermineshafts-fabric-1_18.toml",
    "Size":590,
    "Hash":"b83e0f910b4fe0a6f3aa9ed7ea8eda413022cdd0",
    "DestinationPath":"config/bettermineshafts-fabric-1_18.toml"
  },{
    "File":"armorstands.json",
    "Size":1131,
    "Hash":"154df2ec59d7ac680e6ef0a31c47f4251fc5e62e",
    "DestinationPath":"config/betterstrongholds/fabric-1_18_2/armorstands.json"
  },{
    "File":"itemframes.json",
    "Size":680,
    "Hash":"c8bf5a26de78f54e343c8e5e0b137ca4c23df738",
    "DestinationPath":"config/betterstrongholds/fabric-1_18_2/itemframes.json"
  },{
    "File":"ores.json",
    "Size":346,
    "Hash":"d5477ece0af71334901aaa3bc6229e4033657d39",
    "DestinationPath":"config/betterstrongholds/fabric-1_18_2/ores.json"
  },{
    "File":"rareblocks.json",
    "Size":238,
    "Hash":"0df4cdb9f541299d9ef4e0722555b77096d1de7a",
    "DestinationPath":"config/betterstrongholds/fabric-1_18_2/rareblocks.json"
  },{
    "File":"README.txt",
    "Size":2817,
    "Hash":"e9770e9a6a550871594e7e57326c26a97f912fac",
    "DestinationPath":"config/betterstrongholds/fabric-1_18_2/README.txt"
  },{
    "File":"README.txt",
    "Size":706,
    "Hash":"c998f33867863c69c0ee99af679ecfad189513bd",
    "DestinationPath":"config/betterstrongholds/README.txt"
  },{
    "File":"betterstrongholds-fabric-1_18.toml",
    "Size":487,
    "Hash":"f210359503dc362e7bb6d1a9d34ab39915703bd6",
    "DestinationPath":"config/betterstrongholds-fabric-1_18.toml"
  },{
    "File":"last_working_configs_backup.zip",
    "Size":40850,
    "Hash":"2969aacdb009902c625d4668e89c9399f9e90d5b",
    "DestinationPath":"config/byg/backups/last_working_configs_backup.zip"
  },{
    "File":"biomepedia.json5",
    "Size":517,
    "Hash":"c3894595a9ec6e7d4146abe78841ae6359579459",
    "DestinationPath":"config/byg/biomepedia.json5"
  },{
    "File":"byg-biome-dictionary.json",
    "Size":4365,
    "Hash":"bba413c34037a0d6a8d8723af41f9c2d85f15bc4",
    "DestinationPath":"config/byg/byg-biome-dictionary.json"
  },{
    "File":"biomepedia_inventory.json5",
    "Size":684,
    "Hash":"20d851e124e8f01f40aa4fd4bdde2f27825b58df",
    "DestinationPath":"config/byg/client/biomepedia_inventory.json5"
  },{
    "File":"config_versions.json5",
    "Size":390,
    "Hash":"89c39a9ef602f1009dd308eebadd6ec5fd41e8f4",
    "DestinationPath":"config/byg/config_versions.json5"
  },{
    "File":"end-biomes.json5",
    "Size":3519,
    "Hash":"5aa262538175434f263a0130b7e9bed63cf45b96",
    "DestinationPath":"config/byg/end-biomes.json5"
  },{
    "File":"growing-patterns.json5",
    "Size":63302,
    "Hash":"49e0745933dde7fadc9f468af942c63120edab4c",
    "DestinationPath":"config/byg/growing-patterns.json5"
  },{
    "File":"nether-biomes.json5",
    "Size":5527,
    "Hash":"3e401026576d85d7208d77b2c4c2c0bc9c4716cc",
    "DestinationPath":"config/byg/nether-biomes.json5"
  },{
    "File":"beach_biomes_1.json5",
    "Size":1499,
    "Hash":"df05d8dab38b6d5e5d11130beaf5cc8e4e2005ce",
    "DestinationPath":"config/byg/overworld/biome_selectors/beach_biomes/beach_biomes_1.json5"
  },{
    "File":"beach_biomes_vanilla.json5",
    "Size":1459,
    "Hash":"102280a33aad0819a01bffbe74d1f39b9d18d4d3",
    "DestinationPath":"config/byg/overworld/biome_selectors/beach_biomes/beach_biomes_vanilla.json5"
  },{
    "File":"middle_biomes_1.json5",
    "Size":1577,
    "Hash":"342e04bdd8f51bd4773251f6daab506f80ec693d",
    "DestinationPath":"config/byg/overworld/biome_selectors/middle_biomes/middle_biomes_1.json5"
  },{
    "File":"middle_biomes_2.json5",
    "Size":1596,
    "Hash":"247a8de7eb4e78179fe68fe1bb634c5d062b3c72",
    "DestinationPath":"config/byg/overworld/biome_selectors/middle_biomes/middle_biomes_2.json5"
  },{
    "File":"middle_biomes_3.json5",
    "Size":1574,
    "Hash":"6d544cdab5a187fed201c96e8c77958c549614ac",
    "DestinationPath":"config/byg/overworld/biome_selectors/middle_biomes/middle_biomes_3.json5"
  },{
    "File":"middle_biomes_vanilla.json5",
    "Size":1575,
    "Hash":"90adb4a6adafc27dcc2afccf7a81dfd3c1fa2d93",
    "DestinationPath":"config/byg/overworld/biome_selectors/middle_biomes/middle_biomes_vanilla.json5"
  },{
    "File":"middle_biomes_variant_vanilla.json5",
    "Size":1605,
    "Hash":"fb250a3dc778f11316144180601f8cc1bfa132ac",
    "DestinationPath":"config/byg/overworld/biome_selectors/middle_biomes_variant/middle_biomes_variant_vanilla.json5"
  },{
    "File":"oceans_1.json5",
    "Size":932,
    "Hash":"948258aa4ba3ed2fb012d77b5cf6287b649ad46c",
    "DestinationPath":"config/byg/overworld/biome_selectors/oceans/oceans_1.json5"
  },{
    "File":"oceans_vanilla.json5",
    "Size":1016,
    "Hash":"8a4aa6288297921564524d3f305245142dc64d40",
    "DestinationPath":"config/byg/overworld/biome_selectors/oceans/oceans_vanilla.json5"
  },{
    "File":"peak_biomes_1.json5",
    "Size":1529,
    "Hash":"c9ca7a5b4bf0b8db2f74380d4e52a7decc8782c8",
    "DestinationPath":"config/byg/overworld/biome_selectors/peak_biomes/peak_biomes_1.json5"
  },{
    "File":"peak_biomes_vanilla.json5",
    "Size":1616,
    "Hash":"61792456542d8b68a27dd9b1e57a88eb53ef59b8",
    "DestinationPath":"config/byg/overworld/biome_selectors/peak_biomes/peak_biomes_vanilla.json5"
  },{
    "File":"peak_biomes_variant_vanilla.json5",
    "Size":1646,
    "Hash":"2b0b4e60121600715aa9386c2fef1f28da2e1767",
    "DestinationPath":"config/byg/overworld/biome_selectors/peak_biomes_variant/peak_biomes_variant_vanilla.json5"
  },{
    "File":"plateau_biomes_1.json5",
    "Size":1593,
    "Hash":"e61c32969fc160789b7586a49c4b962a76685444",
    "DestinationPath":"config/byg/overworld/biome_selectors/plateau_biomes/plateau_biomes_1.json5"
  },{
    "File":"plateau_biomes_2.json5",
    "Size":1589,
    "Hash":"92d633dd7bece91ac9c2d4021bcef12e9f1b749e",
    "DestinationPath":"config/byg/overworld/biome_selectors/plateau_biomes/plateau_biomes_2.json5"
  },{
    "File":"plateau_biomes_3.json5",
    "Size":1589,
    "Hash":"92d633dd7bece91ac9c2d4021bcef12e9f1b749e",
    "DestinationPath":"config/byg/overworld/biome_selectors/plateau_biomes/plateau_biomes_3.json5"
  },{
    "File":"plateau_biomes_vanilla.json5",
    "Size":1623,
    "Hash":"9329bbf5d90a3a8ab54925481e2f106a7d4604ee",
    "DestinationPath":"config/byg/overworld/biome_selectors/plateau_biomes/plateau_biomes_vanilla.json5"
  },{
    "File":"plateau_biomes_variant_vanilla.json5",
    "Size":1599,
    "Hash":"89bc6e0da9ce0ecf7829838f6863226616e767a5",
    "DestinationPath":"config/byg/overworld/biome_selectors/plateau_biomes_variant/plateau_biomes_variant_vanilla.json5"
  },{
    "File":"shattered_biomes_vanilla.json5",
    "Size":1689,
    "Hash":"71fc3dd346a8ff7e0963cc708c49dd1532cdab29",
    "DestinationPath":"config/byg/overworld/biome_selectors/shattered_biomes/shattered_biomes_vanilla.json5"
  },{
    "File":"slope_biomes_1.json5",
    "Size":1538,
    "Hash":"1af2e91f5641edb0c2e9fae7d248b523fd6796b4",
    "DestinationPath":"config/byg/overworld/biome_selectors/slope_biomes/slope_biomes_1.json5"
  },{
    "File":"slope_biomes_vanilla.json5",
    "Size":1555,
    "Hash":"e76c48044c70c5378a07407c085af5bd408c6990",
    "DestinationPath":"config/byg/overworld/biome_selectors/slope_biomes/slope_biomes_vanilla.json5"
  },{
    "File":"slope_biomes_variant_vanilla.json5",
    "Size":1601,
    "Hash":"f3b8c06ff709cd08a7be70510ce8c427e0508247",
    "DestinationPath":"config/byg/overworld/biome_selectors/slope_biomes_variant/slope_biomes_variant_vanilla.json5"
  },{
    "File":"byg-overworld-biomes.json5",
    "Size":682,
    "Hash":"a120d54333201a93c75332fb51e0f1867fd0d697",
    "DestinationPath":"config/byg/overworld/byg-overworld-biomes.json5"
  },{
    "File":"region_1.json5",
    "Size":7334,
    "Hash":"f6ce303295cc7d431b7a66edba5a9f5e7d458bfc",
    "DestinationPath":"config/byg/overworld/regions/region_1.json5"
  },{
    "File":"region_2.json5",
    "Size":7344,
    "Hash":"d5c9d4364f18088a39aae56acdf4e758f05aaa74",
    "DestinationPath":"config/byg/overworld/regions/region_2.json5"
  },{
    "File":"region_3.json5",
    "Size":7280,
    "Hash":"7516832d0a11b0ea0fe2dc3e63ffc2080274c75e",
    "DestinationPath":"config/byg/overworld/regions/region_3.json5"
  },{
    "File":"README.txt",
    "Size":108,
    "Hash":"748716cdc4378ace7f71120a392454dee4398f8b",
    "DestinationPath":"config/byg/README.txt"
  },{
    "File":"settings.json5",
    "Size":1865,
    "Hash":"06f1ee7fa1ac0014d3e4129c6c1c3b018ab32b14",
    "DestinationPath":"config/byg/settings.json5"
  },{
    "File":"end_surface_rules.json5",
    "Size":6482,
    "Hash":"c5ebac837ad7d236defc03aeea5d4c7e9f123ec9",
    "DestinationPath":"config/byg/surface_rules/end_surface_rules.json5"
  },{
    "File":"nether_surface_rules.json5",
    "Size":23985,
    "Hash":"b403c6bdf572618eff45eb4c516f11ddc8358b9f",
    "DestinationPath":"config/byg/surface_rules/nether_surface_rules.json5"
  },{
    "File":"overworld_surface_rules.json5",
    "Size":80367,
    "Hash":"cce84ac9a14f0e1c279266772dcc34c30e837b04",
    "DestinationPath":"config/byg/surface_rules/overworld_surface_rules.json5"
  },{
    "File":"trades.json5",
    "Size":14781,
    "Hash":"27d71ee9f99f41f3d89e7efd2053d52b9dc689d1",
    "DestinationPath":"config/byg/trades.json5"
  },{
    "File":"c2me-compat.toml",
    "Size":2,
    "Hash":"ba8ab5a0280b953aa97435ff8946cbcbb2755a27",
    "DestinationPath":"config/c2me-compat.toml"
  },{
    "File":"c2me.toml",
    "Size":4651,
    "Hash":"9de357a417619eb05d90cd24603cdab4333896d7",
    "DestinationPath":"config/c2me.toml"
  },{
    "File":"default_carpet-fixes.conf",
    "Size":0,
    "Hash":"da39a3ee5e6b4b0d3255bfef95601890afd80709",
    "DestinationPath":"config/carpet/default_carpet-fixes.conf"
  },{
    "File":"default_carpet.conf",
    "Size":0,
    "Hash":"da39a3ee5e6b4b0d3255bfef95601890afd80709",
    "DestinationPath":"config/carpet/default_carpet.conf"
  },{
    "File":"cleardespawn.toml",
    "Size":58,
    "Hash":"e2a93eb32e885e6f2963b07bccdb3eef0c88a605",
    "DestinationPath":"config/cleardespawn.toml"
  },{
    "File":"biomepedia.dat",
    "Size":27,
    "Hash":"c554d6fb489e8b521c0679a69e3c85007c175559",
    "DestinationPath":"config/client_data/byg/biomepedia.dat"
  },{
    "File":"computercraft-client.toml",
    "Size":377,
    "Hash":"a7d2f24f27c15bdce4ef7197959eb207a06f0697",
    "DestinationPath":"config/computercraft-client.toml"
  },{
    "File":"create-client.toml",
    "Size":4508,
    "Hash":"22a2047aa2b83f8b31461ee2469bb602bdaef365",
    "DestinationPath":"config/create-client.toml"
  },{
    "File":"create-common.toml",
    "Size":1245,
    "Hash":"4b122c519421a07f13960898fe969aaef4d64cc6",
    "DestinationPath":"config/create-common.toml"
  },{
    "File":"createaddition-common.toml",
    "Size":4133,
    "Hash":"30c4910766f424ac30c7802fa5349cdf03dd5c40",
    "DestinationPath":"config/createaddition-common.toml"
  },{
    "File":"croptopia.conf",
    "Size":9569,
    "Hash":"8d7d236334e2f9b38366007f722d2b7539fb9bda",
    "DestinationPath":"config/croptopia/croptopia.conf"
  },{
    "File":"features.json",
    "Size":30,
    "Hash":"64770bca8f9d8a6fe9f1fd52816bc1d741f1e905",
    "DestinationPath":"config/dawn/features.json"
  },{
    "File":"effective.json",
    "Size":153,
    "Hash":"4f7e9c0e03d8f753897b001741e19379d05386a4",
    "DestinationPath":"config/effective.json"
  },{
    "File":"expandedstorage.json",
    "Size":136,
    "Hash":"acc9c9936fbd2f07ddf7a76ee5641d589e60c240",
    "DestinationPath":"config/expandedstorage.json"
  },{
    "File":"expanded_armor_enchanting.json",
    "Size":44,
    "Hash":"7e9572f7b4c252dbf45438b27f41c1e093de4c90",
    "DestinationPath":"config/expanded_armor_enchanting.json"
  },{
    "File":"expanded_axe_enchanting.json",
    "Size":97,
    "Hash":"da0a399855d3147a1ddc6cec238c1b7f4f0f67f5",
    "DestinationPath":"config/expanded_axe_enchanting.json"
  },{
    "File":"expanded_trident_enchanting.json",
    "Size":163,
    "Hash":"884f6bcfb5c03390a640fbb95703ac7704f1c945",
    "DestinationPath":"config/expanded_trident_enchanting.json"
  },{
    "File":"expanded_weapon_enchanting.json",
    "Size":51,
    "Hash":"9ae62ca84f56caec6137a45ccedd15220bd13c8c",
    "DestinationPath":"config/expanded_weapon_enchanting.json"
  },{
    "File":"indigo-renderer.properties",
    "Size":258,
    "Hash":"e57120a53c9edc73e3fdef2d761d8f81072a3cec",
    "DestinationPath":"config/fabric/indigo-renderer.properties"
  },{
    "File":"ferritecore.mixin.properties",
    "Size":1407,
    "Hash":"768afe6b2baa22f3cc091cde5057871a81cda563",
    "DestinationPath":"config/ferritecore.mixin.properties"
  },{
    "File":"flywheel.json",
    "Size":77,
    "Hash":"3b8502d69f21cac5893c7178f5512c5a6eeab1fb",
    "DestinationPath":"config/flywheel.json"
  },{
    "File":"friendsandfoes.json",
    "Size":1176,
    "Hash":"84bfc17629102cebdd2add613d55879bcfd84a79",
    "DestinationPath":"config/friendsandfoes.json"
  },{
    "File":"highlighter.json5",
    "Size":345,
    "Hash":"e70f500b3e0d013da489671812d1493d40c8dfc4",
    "DestinationPath":"config/highlighter.json5"
  },{
    "File":"illuminations.properties",
    "Size":3761,
    "Hash":"a7603c9f2a21706b0f7db2d070eb974bee847233",
    "DestinationPath":"config/illuminations.properties"
  },{
    "File":"indium-renderer.properties",
    "Size":256,
    "Hash":"c0ff2e68425be0b07277bb4b1781affaefb21fb8",
    "DestinationPath":"config/indium-renderer.properties"
  },{
    "File":"inmis.json",
    "Size":2911,
    "Hash":"85bf2877fabf155a8dc625df490572605cecfaf6",
    "DestinationPath":"config/inmis.json"
  },{
    "File":"exampleIntegrationHints.json",
    "Size":1450,
    "Hash":"2bedb4d58a778b937dd9da01c50a46af9887709b",
    "DestinationPath":"config/inventoryprofilesnext/integrationHints/exampleIntegrationHints.json"
  },{
    "File":"inventoryprofiles.json",
    "Size":218,
    "Hash":"6aec99727fd8fbd4d0912082a6be5d5d1a8b3bfb",
    "DestinationPath":"config/inventoryprofilesnext/inventoryprofiles.json"
  },{
    "File":"lambdabettergrass.toml",
    "Size":296,
    "Hash":"ac8c39d00ebba9eee7e371a37d28086433b65799",
    "DestinationPath":"config/lambdabettergrass.toml"
  },{
    "File":"lambdynlights.toml",
    "Size":3922,
    "Hash":"5c49dc6a22bd02a66cb0ebbdcb324a4b4469ac8b",
    "DestinationPath":"config/lambdynlights.toml"
  },{
    "File":"libgui.json5",
    "Size":101,
    "Hash":"aa2f828b3903fa48180cb314feb1107f4b4e42f2",
    "DestinationPath":"config/libgui.json5"
  },{
    "File":"lithium.properties",
    "Size":350,
    "Hash":"f4bb492c4e567251583252fffdbded3a6d441d2e",
    "DestinationPath":"config/lithium.properties"
  },{
    "File":"modmenu.json",
    "Size":486,
    "Hash":"68d1e6fc66a9fe284b86f0fbfea6a35048f646a3",
    "DestinationPath":"config/modmenu.json"
  },{
    "File":"morevillagers.toml",
    "Size":307,
    "Hash":"0c6ab8116b1f3452aac73599c7b8db68617a47c7",
    "DestinationPath":"config/morevillagers.toml"
  },{
    "File":"noindium.json",
    "Size":472,
    "Hash":"05c6653be90272ade305f34dd1fed83e5688d15b",
    "DestinationPath":"config/noindium.json"
  },{
    "File":"ok_zoomer.json5",
    "Size":3077,
    "Hash":"89a6c2cd01a7749ab778e0c4da03edadcdf8330b",
    "DestinationPath":"config/ok_zoomer.json5"
  },{
    "File":"peripheralium-common.toml",
    "Size":571,
    "Hash":"a3ff12283fc565bcf00d694ae3cbed89f162138e",
    "DestinationPath":"config/peripheralium-common.toml"
  },{
    "File":"peripheralworks-common.toml",
    "Size":1295,
    "Hash":"16c8f5aafc82a2f4b955bf21337e89fea41761d1",
    "DestinationPath":"config/peripheralworks-common.toml"
  },{
    "File":"client.json",
    "Size":379,
    "Hash":"d2dd8a4fb19c19cb1642d7f7f3b08a53a5c6279c",
    "DestinationPath":"config/polymer/client.json"
  },{
    "File":"server.json",
    "Size":1426,
    "Hash":"8db53bdbcaa050febcd1ca80befc2f391041dbb5",
    "DestinationPath":"config/polymer/server.json"
  },{
    "File":"polymorph-integrations.json",
    "Size":553,
    "Hash":"f285bea0dc0989ebf24b7d4bb64347ef34e57fcd",
    "DestinationPath":"config/polymorph-integrations.json"
  },{
    "File":"probablychests.json",
    "Size":251,
    "Hash":"89d067ab88e49d1c8cd859baf95e9057b197ae90",
    "DestinationPath":"config/probablychests.json"
  },{
    "File":"respawnablepets.json",
    "Size":25,
    "Hash":"91da955e96a8706bc52e762179c737ef6a9f1e8a",
    "DestinationPath":"config/respawnablepets.json"
  },{
    "File":"config.json5",
    "Size":6064,
    "Hash":"8b59557b8699ae5c49c4254d6c7161e0ef3970da",
    "DestinationPath":"config/roughlyenoughitems/config.json5"
  },{
    "File":"skinlayers.json",
    "Size":366,
    "Hash":"a9c360a5d3f5f66b4d9a7b62cb2723cfdda52177",
    "DestinationPath":"config/skinlayers.json"
  },{
    "File":"smoothswapping.json",
    "Size":74,
    "Hash":"a3b135f7908c976b5433882a3c5e17a06a0c030f",
    "DestinationPath":"config/smoothswapping.json"
  },{
    "File":"sodium-mixins.properties",
    "Size":266,
    "Hash":"09db7f09d6dfd063ec4c7c534102892d67655d98",
    "DestinationPath":"config/sodium-mixins.properties"
  },{
    "File":"sodium-options.json",
    "Size":659,
    "Hash":"93ca40d20769fef06a59a289f0d90d7377ce44cc",
    "DestinationPath":"config/sodium-options.json"
  },{
    "File":"occlusion.properties",
    "Size":1251,
    "Hash":"ee4260d2c6aabe35bb98bb3514b1e1ac5ed4e4fd",
    "DestinationPath":"config/sound_physics_remastered/occlusion.properties"
  },{
    "File":"reflectivity.properties",
    "Size":1254,
    "Hash":"8c16a76db1767095d633b9ce34b614ea6deff8bf",
    "DestinationPath":"config/sound_physics_remastered/reflectivity.properties"
  },{
    "File":"soundphysics.properties",
    "Size":770,
    "Hash":"f9bc3e1bc70efdbfdb3cbb5e6e9e256b8466388e",
    "DestinationPath":"config/sound_physics_remastered/soundphysics.properties"
  },{
    "File":"stendhal.properties",
    "Size":323,
    "Hash":"bc1f0c05b90b80f434109cec84272adb76428bcd",
    "DestinationPath":"config/stendhal/stendhal.properties"
  },{
    "File":"terrablender.toml",
    "Size":552,
    "Hash":"9170b19e75cded7b1d6229f44f1abb43a256d863",
    "DestinationPath":"config/terrablender.toml"
  },{
    "File":"tr7zwDonorSettings.json",
    "Size":37,
    "Hash":"6d1993e730a8f0e0b531b49bf0014fb9cdbc2f8f",
    "DestinationPath":"config/tr7zwDonorSettings.json"
  },{
    "File":"trade_cycling.properties",
    "Size":74,
    "Hash":"9b55883a3f267e77a2321bd57b809dd85e8aa67f",
    "DestinationPath":"config/trade_cycling/trade_cycling.properties"
  },{
    "File":"translated_server.json",
    "Size":30,
    "Hash":"be7ca20068140501ecea2a556cb9b2d1845584d3",
    "DestinationPath":"config/translated_server.json"
  },{
    "File":"turtlematic-common.toml",
    "Size":4116,
    "Hash":"8df71798ca95d87709f4dcef84d6cc902a02f779",
    "DestinationPath":"config/turtlematic-common.toml"
  },{
    "File":"veinmining.json5",
    "Size":4027,
    "Hash":"803b73d9210525d6a5f4b215ed66cec3e2c346ea",
    "DestinationPath":"config/veinmining.json5"
  },{
    "File":"username-cache.json",
    "Size":155,
    "Hash":"f007d8e5435bf0216057ae4f09960fffafd58ded",
    "DestinationPath":"config/voicechat/username-cache.json"
  },{
    "File":"voicechat-client.properties",
    "Size":894,
    "Hash":"7321ffa069ebd2becb10420c495a2a0a8fc41e63",
    "DestinationPath":"config/voicechat/voicechat-client.properties"
  },{
    "File":"voicechat-server.properties",
    "Size":425,
    "Hash":"3d540d5fa3c8aaed95a40d2c51e194068bfbfbca",
    "DestinationPath":"config/voicechat/voicechat-server.properties"
  },{
    "File":"blacklist.json",
    "Size":361,
    "Hash":"1128a7a6ba3b485802dae4c5b9850d313cebc5d3",
    "DestinationPath":"config/waila/blacklist.json"
  },{
    "File":"waila.json",
    "Size":1205,
    "Hash":"73b9767e4084296ca1a33cd3eccb6384f9728003",
    "DestinationPath":"config/waila/waila.json"
  },{
    "File":"waila_plugins.json",
    "Size":870,
    "Hash":"b17f37a886b53e86ef9fa43483cc6f010fd7cbcb",
    "DestinationPath":"config/waila/waila_plugins.json"
  },{
    "File":"config.json",
    "Size":1421,
    "Hash":"1bd7949d51225f8aa21f4ad222484acb8f8e0e8d",
    "DestinationPath":"config/waystones/config.json"
  },{
    "File":"worldedit.properties",
    "Size":2513,
    "Hash":"3e4d2ca5ef7069ad94313b9d892f50ae282dc9fc",
    "DestinationPath":"config/worldedit/worldedit.properties"
  },{
    "File":"yungsbridges-fabric-1_18.toml",
    "Size":91,
    "Hash":"260199429878c47b6051b55b4fba3a24e5b21e23",
    "DestinationPath":"config/yungsbridges-fabric-1_18.toml"
  },{
    "File":"README.txt",
    "Size":1357,
    "Hash":"cb6d3e79a2086a084cff2ebe95a1f6df79296498",
    "DestinationPath":"config/YungsExtras/fabric-1_18/README.txt"
  },{
    "File":"wishing_wells.json",
    "Size":202,
    "Hash":"43a289775c4d482251e13b1c628cc40f6366997c",
    "DestinationPath":"config/YungsExtras/fabric-1_18/wishing_wells.json"
  },{
    "File":"README.txt",
    "Size":679,
    "Hash":"94fdfa842b1ed7e31e6b86b1c59813661e15f544",
    "DestinationPath":"config/YungsExtras/README.txt"
  },{
    "File":"yungsextras-fabric-1_18.toml",
    "Size":851,
    "Hash":"fe8bac1c250a5f0d03586550754652478a4bedea",
    "DestinationPath":"config/yungsextras-fabric-1_18.toml"
  },{
    "File":"3D Backpacks.zip",
    "Size":99235,
    "Hash":"9105d3219a924e3f0534ed6444b698a076d846e1",
    "DestinationPath":"resourcepacks/3D Backpacks.zip"
  },{
    "File":"Copper Legacy Pack.zip",
    "Size":6804,
    "Hash":"1af57dfd834df79d7bc822e307cbb011163f6615",
    "DestinationPath":"resourcepacks/Copper Legacy Pack.zip"
  },{
    "File":"infested-stone-resources-1-17-v2-0.zip",
    "Size":11160,
    "Hash":"bfe165d3dda520139187f5b7e55c4aa826f42495",
    "DestinationPath":"resourcepacks/infested-stone-resources-1-17-v2-0.zip"
  },{
    "File":"options.txt",
    "Size":5028,
    "Hash":"81f37df8e2a7554df828b6106062b357227da16f",
    "DestinationPath":"options.txt"
  },{
    "File":"servers.dat",
    "Size":137,
    "Hash":"295f1d5b7d9d0a8a34fa106fbbc8911557e1e1ed",
    "DestinationPath":"servers.dat"
  }]